linops/__init__.py
linops/block_minres.py
linops/blocks.py
linops/cg.py
linops/diag.py
linops/equilibration.py
linops/linop_impls.py
linops/linops.py
linops/lsqr.py
linops/minres.py
linops/nystrom_precondition.py
linops/trace.py
torch_linops-0.2.0.dist-info/METADATA
torch_linops-0.2.0.dist-info/WHEEL
torch_linops-0.2.0.dist-info/top_level.txt
torch_linops-0.2.0.dist-info/RECORD
