Metadata-Version: 2.4
Name: torch-linops
Version: 0.2.0
Summary: A library to define abstract linear operators, and associated algebra and matrix-free algorithms, that works with pyTorch Tensors.
Author-email: Parth Nobel <ptnobel@stanford.edu>
License-Expression: Apache-2.0
Classifier: Programming Language :: Python :: 3
Requires-Dist: torch>=2.0.0
